pytket/extensions/offline_display/__init__.py
pytket/extensions/offline_display/dist/main.js
pytket/extensions/offline_display/dist/main.js.LICENSE.txt
pytket/extensions/offline_display/js/index.js
pytket/extensions/offline_display/static/head_imports.html
pytket_offline_display-0.0.9.dist-info/METADATA
pytket_offline_display-0.0.9.dist-info/WHEEL
pytket_offline_display-0.0.9.dist-info/top_level.txt
pytket_offline_display-0.0.9.dist-info/RECORD
