Metadata-Version: 2.1
Name: pytket-offline-display
Version: 0.0.9
Summary: Python module for displaying pytket circuits when offline.
Author: TKET development team
Author-email: tket-support@cambridgequantum.com
License: Apache 2
Project-URL: Documentation, https://cqcl.github.io/tket/pytket/api/index.html
Project-URL: Source, https://github.com/CQCL/pytket-offline-renderer
Project-URL: Tracker, https://github.com/CQCL/pytket-offline-renderer/issues
Requires-Python: >=3.9
Requires-Dist: jinja2~=3.0
Requires-Dist: pytket>=1.31.1
